kalabash_radicale/__init__.py
kalabash_radicale/apps.py
kalabash_radicale/factories.py
kalabash_radicale/forms.py
kalabash_radicale/handlers.py
kalabash_radicale/kbash_extension.py
kalabash_radicale/mocks.py
kalabash_radicale/models.py
kalabash_radicale/serializers.py
kalabash_radicale/settings.py
kalabash_radicale/tests.py
kalabash_radicale/urls.py
kalabash_radicale/urls_api.py
kalabash_radicale/views.py
kalabash_radicale/viewsets.py
kalabash_radicale/backends/__init__.py
kalabash_radicale/backends/caldav_.py
kalabash_radicale/locale/br/LC_MESSAGES/django.mo
kalabash_radicale/locale/br/LC_MESSAGES/django.po
kalabash_radicale/locale/cs_CZ/LC_MESSAGES/django.mo
kalabash_radicale/locale/cs_CZ/LC_MESSAGES/django.po
kalabash_radicale/locale/de/LC_MESSAGES/django.mo
kalabash_radicale/locale/de/LC_MESSAGES/django.po
kalabash_radicale/locale/en/LC_MESSAGES/django.mo
kalabash_radicale/locale/en/LC_MESSAGES/django.po
kalabash_radicale/locale/es/LC_MESSAGES/django.mo
kalabash_radicale/locale/es/LC_MESSAGES/django.po
kalabash_radicale/locale/fr/LC_MESSAGES/django.mo
kalabash_radicale/locale/fr/LC_MESSAGES/django.po
kalabash_radicale/locale/it/LC_MESSAGES/django.mo
kalabash_radicale/locale/it/LC_MESSAGES/django.po
kalabash_radicale/locale/nl_NL/LC_MESSAGES/django.mo
kalabash_radicale/locale/nl_NL/LC_MESSAGES/django.po
kalabash_radicale/locale/pt_BR/LC_MESSAGES/django.mo
kalabash_radicale/locale/pt_BR/LC_MESSAGES/django.po
kalabash_radicale/locale/pt_PT/LC_MESSAGES/django.mo
kalabash_radicale/locale/pt_PT/LC_MESSAGES/django.po
kalabash_radicale/locale/ro_RO/LC_MESSAGES/django.mo
kalabash_radicale/locale/ro_RO/LC_MESSAGES/django.po
kalabash_radicale/locale/ru/LC_MESSAGES/django.mo
kalabash_radicale/locale/ru/LC_MESSAGES/django.po
kalabash_radicale/locale/sv/LC_MESSAGES/django.mo
kalabash_radicale/locale/sv/LC_MESSAGES/django.po
kalabash_radicale/locale/zh_TW/LC_MESSAGES/django.mo
kalabash_radicale/locale/zh_TW/LC_MESSAGES/django.po
kalabash_radicale/management/__init__.py
kalabash_radicale-1.6.2.dist-info/LICENSE
kalabash_radicale-1.6.2.dist-info/METADATA
kalabash_radicale-1.6.2.dist-info/WHEEL
kalabash_radicale-1.6.2.dist-info/top_level.txt
kalabash_radicale-1.6.2.dist-info/RECORD
